odoo8_addon_account_bank_statement_import_qif-8.0.1.0.1.99.dev6-py2.7-nspkg.pth
odoo8_addon_account_bank_statement_import_qif-8.0.1.0.1.99.dev6.dist-info/METADATA
odoo8_addon_account_bank_statement_import_qif-8.0.1.0.1.99.dev6.dist-info/RECORD
odoo8_addon_account_bank_statement_import_qif-8.0.1.0.1.99.dev6.dist-info/WHEEL
odoo8_addon_account_bank_statement_import_qif-8.0.1.0.1.99.dev6.dist-info/namespace_packages.txt
odoo8_addon_account_bank_statement_import_qif-8.0.1.0.1.99.dev6.dist-info/top_level.txt
odoo_addons/account_bank_statement_import_qif/README.rst
odoo_addons/account_bank_statement_import_qif/__init__.py
odoo_addons/account_bank_statement_import_qif/__openerp__.py
odoo_addons/account_bank_statement_import_qif/account_bank_statement_import_qif.py
odoo_addons/account_bank_statement_import_qif/i18n/account_bank_statement_import_qif.pot
odoo_addons/account_bank_statement_import_qif/i18n/de.po
odoo_addons/account_bank_statement_import_qif/i18n/es.po
odoo_addons/account_bank_statement_import_qif/i18n/fi.po
odoo_addons/account_bank_statement_import_qif/i18n/fr.po
odoo_addons/account_bank_statement_import_qif/i18n/lt_LT.po
odoo_addons/account_bank_statement_import_qif/i18n/nl.po
odoo_addons/account_bank_statement_import_qif/i18n/pt_BR.po
odoo_addons/account_bank_statement_import_qif/i18n/pt_PT.po
odoo_addons/account_bank_statement_import_qif/i18n/sl.po
odoo_addons/account_bank_statement_import_qif/static/description/icon.png
odoo_addons/account_bank_statement_import_qif/test_qif_file/test_qif.qif
odoo_addons/account_bank_statement_import_qif/tests/__init__.py
odoo_addons/account_bank_statement_import_qif/tests/test_import_bank_statement.py
