Metadata-Version: 2.1
Name: odoo8-addon-account-bank-statement-import-qif
Version: 8.0.1.0.1.99.dev6
Summary: Import QIF Bank Statement
Home-page: https://github.com/OCA/bank-statement-import
Author: OpenERP SA,Odoo Community Association (OCA)
Author-email: support@odoo-community.org
License: AGPL-3
Platform: UNKNOWN
Classifier: Programming Language :: Python
Classifier: Framework :: Odoo
Classifier: License :: OSI Approved :: GNU Affero General Public License v3
Requires-Python: ~=2.7
Requires-Dist: odoo8-addon-account-bank-statement-import
Requires-Dist: odoo (<9.0a,>=8.0a)
